[{"kind": "Listing", "data": {"modhash": "", "whitelist_status": "promo_specified", "children": [{"kind": "t3", "data": {"domain": "self.The_Donald", "approved_at_utc": null, "banned_by": null, "media_embed": {}, "thumbnail_width": null, "subreddit": "The_Donald", "selftext_html": null, "selftext": "", "likes": null, "suggested_sort": null, "user_reports": [], "secure_media": null, "is_reddit_media_domain": false, "link_flair_text": null, "id": "75sdxw", "banned_at_utc": null, "view_count": null, "archived": false, "clicked": false, "report_reasons": null, "title": "After all the rape claims, the FBI raided Democrat Harvey Weinstein they broke down his door with guns drawn, tore him and wife out of bed and executed a search warrant. Oh wait they didn't they let Democrat Harvey leave the country, without lifting a finger", "num_crossposts": 0, "saved": false, "can_mod_post": false, "is_crosspostable": false, "pinned": false, "score": 603, "approved_by": null, "over_18": false, "hidden": false, "num_comments": 4, "thumbnail": "self", "subreddit_id": "t5_38unr", "hide_score": false, "edited": false, "link_flair_css_class": null, "author_flair_css_class": "centi", "contest_mode": false, "gilded": 0, "locked": false, "downs": 0, "brand_safe": false, "secure_media_embed": {}, "removal_reason": null, "can_gild": false, "thumbnail_height": null, "parent_whitelist_status": "promo_specified", "name": "t3_75sdxw", "spoiler": false, "permalink": "/r/The_Donald/comments/75sdxw/after_all_the_rape_claims_the_fbi_raided_democrat/", "num_reports": null, "whitelist_status": "promo_specified", "stickied": false, "created": 1507786990.0, "url": "https://www.reddit.com/r/The_Donald/comments/75sdxw/after_all_the_rape_claims_the_fbi_raided_democrat/", "author_flair_text": null, "quarantine": false, "author": "mivvan", "created_utc": 1507758190.0, "subreddit_name_prefixed": "r/The_Donald", "distinguished": null, "media": null, "upvote_ratio": 0.96, "mod_reports": [], "is_self": true, "visited": false, "subreddit_type": "public", "is_video": false, "ups": 603}}], "after": null, "before": null}}, {"kind": "Listing", "data": {"modhash": "", "whitelist_status": "promo_specified", "children": [{"kind": "t1", "data": {"subreddit_id": "t5_38unr", "approved_at_utc": null, "banned_by": null, "removal_reason": null, "link_id": "t3_75sdxw", "likes": null, "replies": "", "user_reports": [], "saved": false, "id": "do8jycd", "banned_at_utc": null, "gilded": 0, "archived": false, "report_reasons": null, "author": "findthewarmspot", "can_mod_post": false, "ups": 6, "parent_id": "t3_75sdxw", "score": 6, "approved_by": null, "downs": 0, "body": "He's moving next door to roman Polanski ", "edited": false, "author_flair_css_class": null, "collapsed": false, "is_submitter": false, "collapsed_reason": null, "body_html": "&lt;div class=\"md\"&gt;&lt;p&gt;He&amp;#39;s moving next door to roman Polanski &lt;/p&gt;\n&lt;/div&gt;", "stickied": false, "can_gild": true, "subreddit": "The_Donald", "score_hidden": false, "subreddit_type": "public", "name": "t1_do8jycd", "created": 1507787150.0, "author_flair_text": null, "created_utc": 1507758350.0, "subreddit_name_prefixed": "r/The_Donald", "controversiality": 0, "depth": 0, "mod_reports": [], "num_reports": null, "distinguished": null}}, {"kind": "t1", "data": {"subreddit_id": "t5_38unr", "approved_at_utc": null, "banned_by": null, "removal_reason": null, "link_id": "t3_75sdxw", "likes": null, "replies": "", "user_reports": [], "saved": false, "id": "do8r0ba", "banned_at_utc": null, "gilded": 0, "archived": false, "report_reasons": null, "author": "DonDonRump", "can_mod_post": false, "ups": 2, "parent_id": "t3_75sdxw", "score": 2, "approved_by": null, "downs": 0, "body": "We know and trust the FBI, don't we folks?", "edited": false, "author_flair_css_class": null, "collapsed": false, "is_submitter": false, "collapsed_reason": null, "body_html": "&lt;div class=\"md\"&gt;&lt;p&gt;We know and trust the FBI, don&amp;#39;t we folks?&lt;/p&gt;\n&lt;/div&gt;", "stickied": false, "can_gild": true, "subreddit": "The_Donald", "score_hidden": false, "subreddit_type": "public", "name": "t1_do8r0ba", "created": 1507795515.0, "author_flair_text": null, "created_utc": 1507766715.0, "subreddit_name_prefixed": "r/The_Donald", "controversiality": 0, "depth": 0, "mod_reports": [], "num_reports": null, "distinguished": null}}, {"kind": "t1", "data": {"subreddit_id": "t5_38unr", "approved_at_utc": null, "banned_by": null, "removal_reason": null, "link_id": "t3_75sdxw", "likes": null, "replies": "", "user_reports": [], "saved": false, "id": "do8spw8", "banned_at_utc": null, "gilded": 0, "archived": false, "report_reasons": null, "author": "gamerclick", "can_mod_post": false, "ups": 1, "parent_id": "t3_75sdxw", "score": 1, "approved_by": null, "downs": 0, "body": "Let's hold out a day or two... my husband heard about a 911 call this morning and that he may not gone...  I hope it can be confirmed in the next day or two. It was on a podcast (he listens to 100 different ones lol).  I haven't been able to get confirmation here, but I also haven't been able to find where he is in Europe either - which I think would be all over.  Wouldn't it be ironic if he was suicided... He has a LOT of people he could take down with him...\n\nIf he did leave, I think we should go after Polanski AND Weinstein... show them how serious Trump is about cleaning this filth up...", "edited": false, "author_flair_css_class": "MURICA", "collapsed": false, "is_submitter": false, "collapsed_reason": null, "body_html": "&lt;div class=\"md\"&gt;&lt;p&gt;Let&amp;#39;s hold out a day or two... my husband heard about a 911 call this morning and that he may not gone...  I hope it can be confirmed in the next day or two. It was on a podcast (he listens to 100 different ones lol).  I haven&amp;#39;t been able to get confirmation here, but I also haven&amp;#39;t been able to find where he is in Europe either - which I think would be all over.  Wouldn&amp;#39;t it be ironic if he was suicided... He has a LOT of people he could take down with him...&lt;/p&gt;\n\n&lt;p&gt;If he did leave, I think we should go after Polanski AND Weinstein... show them how serious Trump is about cleaning this filth up...&lt;/p&gt;\n&lt;/div&gt;", "stickied": false, "can_gild": true, "subreddit": "The_Donald", "score_hidden": false, "subreddit_type": "public", "name": "t1_do8spw8", "created": 1507797556.0, "author_flair_text": "1776", "created_utc": 1507768756.0, "subreddit_name_prefixed": "r/The_Donald", "controversiality": 0, "depth": 0, "mod_reports": [], "num_reports": null, "distinguished": null}}, {"kind": "t1", "data": {"subreddit_id": "t5_38unr", "approved_at_utc": null, "banned_by": null, "removal_reason": null, "link_id": "t3_75sdxw", "likes": null, "replies": "", "user_reports": [], "saved": false, "id": "do8vztx", "banned_at_utc": null, "gilded": 0, "archived": false, "report_reasons": null, "author": "luvfreed", "can_mod_post": false, "ups": 1, "parent_id": "t3_75sdxw", "score": 1, "approved_by": null, "downs": 0, "body": "Ok Mr Smarty pants.  What cause would the FBI have to raid this guy?  What crime.  You might as well be calling for impeachment with out probably case.  Go post on some progressive site.  And why the FBI.  Did he kidnap someone and take them across state lines?  Perhaps they should invoke marshal law to deal with this.  Fucking pay attention to real issues not this dribble of ranch dressing on monica's blue dress.", "edited": false, "author_flair_css_class": null, "collapsed": false, "is_submitter": false, "collapsed_reason": null, "body_html": "&lt;div class=\"md\"&gt;&lt;p&gt;Ok Mr Smarty pants.  What cause would the FBI have to raid this guy?  What crime.  You might as well be calling for impeachment with out probably case.  Go post on some progressive site.  And why the FBI.  Did he kidnap someone and take them across state lines?  Perhaps they should invoke marshal law to deal with this.  Fucking pay attention to real issues not this dribble of ranch dressing on monica&amp;#39;s blue dress.&lt;/p&gt;\n&lt;/div&gt;", "stickied": false, "can_gild": true, "subreddit": "The_Donald", "score_hidden": false, "subreddit_type": "public", "name": "t1_do8vztx", "created": 1507801486.0, "author_flair_text": null, "created_utc": 1507772686.0, "subreddit_name_prefixed": "r/The_Donald", "controversiality": 0, "depth": 0, "mod_reports": [], "num_reports": null, "distinguished": null}}], "after": null, "before": null}}]