[{"kind": "Listing", "data": {"modhash": "", "whitelist_status": "promo_specified", "children": [{"kind": "t3", "data": {"domain": "i.redd.it", "approved_at_utc": null, "banned_by": null, "media_embed": {}, "thumbnail_width": 140, "subreddit": "The_Donald", "selftext_html": null, "selftext": "", "likes": null, "suggested_sort": null, "user_reports": [], "secure_media": null, "is_reddit_media_domain": true, "link_flair_text": "YUUUUGE!", "id": "75v6n8", "banned_at_utc": null, "view_count": null, "archived": false, "clicked": false, "report_reasons": null, "title": "\u201cThe country has to know the truth.\u201d - President Donald J. Trump 10/11/17", "num_crossposts": 0, "saved": false, "can_mod_post": false, "is_crosspostable": false, "pinned": false, "score": 58, "approved_by": null, "over_18": false, "hidden": false, "preview": {"images": [{"source": {"url": "https://i.redditmedia.com/kAsbKgKP8t71aqE6tXbFVn1J_CZIbwvcNbS-uVDXstU.jpg?s=ce74511c52238517e70184fde4157cdf", "width": 259, "height": 195}, "resolutions": [{"url": "https://i.redditmedia.com/kAsbKgKP8t71aqE6tXbFVn1J_CZIbwvcNbS-uVDXstU.jpg?fit=crop&amp;crop=faces%2Centropy&amp;arh=2&amp;w=108&amp;s=23352528e8ff96d1f33fb0cb30602032", "width": 108, "height": 81}, {"url": "https://i.redditmedia.com/kAsbKgKP8t71aqE6tXbFVn1J_CZIbwvcNbS-uVDXstU.jpg?fit=crop&amp;crop=faces%2Centropy&amp;arh=2&amp;w=216&amp;s=2c4639092cadb988ad193d8d6d2b07f9", "width": 216, "height": 162}], "variants": {}, "id": "xAoOTHA_6viCkotoXjQBgfN8QcgQab40rp7C_0w8l78"}], "enabled": true}, "num_comments": 3, "thumbnail": "https://b.thumbs.redditmedia.com/SppnNZQtA9l8QsraXs9TMC3lyU9YHYkUlx5b1XLgjmI.jpg", "subreddit_id": "t5_38unr", "hide_score": false, "edited": false, "link_flair_css_class": "", "author_flair_css_class": null, "contest_mode": false, "gilded": 0, "locked": false, "downs": 0, "brand_safe": false, "secure_media_embed": {}, "removal_reason": null, "post_hint": "image", "can_gild": false, "thumbnail_height": 105, "parent_whitelist_status": "promo_specified", "name": "t3_75v6n8", "spoiler": false, "permalink": "/r/The_Donald/comments/75v6n8/the_country_has_to_know_the_truth_president/", "num_reports": null, "whitelist_status": "promo_specified", "stickied": false, "created": 1507818206.0, "url": "https://i.redd.it/ys21gliiecrz.jpg", "author_flair_text": null, "quarantine": false, "author": "LA_Trump", "created_utc": 1507789406.0, "subreddit_name_prefixed": "r/The_Donald", "distinguished": null, "media": null, "upvote_ratio": 0.83, "mod_reports": [], "is_self": false, "visited": false, "subreddit_type": "public", "is_video": false, "ups": 58}}], "after": null, "before": null}}, {"kind": "Listing", "data": {"modhash": "", "whitelist_status": "promo_specified", "children": [{"kind": "t1", "data": {"subreddit_id": "t5_38unr", "approved_at_utc": null, "banned_by": null, "removal_reason": null, "link_id": "t3_75v6n8", "likes": null, "replies": {"kind": "Listing", "data": {"modhash": "", "whitelist_status": "promo_specified", "children": [{"kind": "t1", "data": {"subreddit_id": "t5_38unr", "approved_at_utc": null, "banned_by": null, "removal_reason": null, "link_id": "t3_75v6n8", "likes": null, "replies": "", "user_reports": [], "saved": false, "id": "do9aix5", "banned_at_utc": null, "gilded": 0, "archived": false, "report_reasons": null, "author": "LA_Trump", "can_mod_post": false, "ups": 1, "parent_id": "t1_do97q5d", "score": 1, "approved_by": null, "downs": 0, "body": "Yes", "edited": false, "author_flair_css_class": null, "collapsed": false, "is_submitter": true, "collapsed_reason": null, "body_html": "&lt;div class=\"md\"&gt;&lt;p&gt;Yes&lt;/p&gt;\n&lt;/div&gt;", "stickied": false, "can_gild": true, "subreddit": "The_Donald", "score_hidden": false, "subreddit_type": "public", "name": "t1_do9aix5", "created": 1507826789.0, "author_flair_text": null, "created_utc": 1507797989.0, "subreddit_name_prefixed": "r/The_Donald", "controversiality": 0, "depth": 1, "mod_reports": [], "num_reports": null, "distinguished": null}}], "after": null, "before": null}}, "user_reports": [], "saved": false, "id": "do97q5d", "banned_at_utc": null, "gilded": 0, "archived": false, "report_reasons": null, "author": "NECC_EOD", "can_mod_post": false, "ups": 3, "parent_id": "t3_75v6n8", "score": 3, "approved_by": null, "downs": 0, "body": "He said this?", "edited": false, "author_flair_css_class": "usnavy", "collapsed": false, "is_submitter": false, "collapsed_reason": null, "body_html": "&lt;div class=\"md\"&gt;&lt;p&gt;He said this?&lt;/p&gt;\n&lt;/div&gt;", "stickied": false, "can_gild": true, "subreddit": "The_Donald", "score_hidden": false, "subreddit_type": "public", "name": "t1_do97q5d", "created": 1507819488.0, "author_flair_text": "NAVY", "created_utc": 1507790688.0, "subreddit_name_prefixed": "r/The_Donald", "controversiality": 0, "depth": 0, "mod_reports": [], "num_reports": null, "distinguished": null}}, {"kind": "t1", "data": {"subreddit_id": "t5_38unr", "approved_at_utc": null, "banned_by": null, "removal_reason": null, "link_id": "t3_75v6n8", "likes": null, "replies": "", "user_reports": [], "saved": false, "id": "do9klx0", "banned_at_utc": null, "gilded": 0, "archived": false, "report_reasons": null, "author": "SquirmaMita", "can_mod_post": false, "ups": 1, "parent_id": "t3_75v6n8", "score": 1, "approved_by": null, "downs": 0, "body": "Sauce?", "edited": false, "author_flair_css_class": "MURICA", "collapsed": false, "is_submitter": false, "collapsed_reason": null, "body_html": "&lt;div class=\"md\"&gt;&lt;p&gt;Sauce?&lt;/p&gt;\n&lt;/div&gt;", "stickied": false, "can_gild": true, "subreddit": "The_Donald", "score_hidden": false, "subreddit_type": "public", "name": "t1_do9klx0", "created": 1507846169.0, "author_flair_text": "MAGA", "created_utc": 1507817369.0, "subreddit_name_prefixed": "r/The_Donald", "controversiality": 0, "depth": 0, "mod_reports": [], "num_reports": null, "distinguished": null}}], "after": null, "before": null}}]